WuyunZhishikuDiyiBufen/README.md
WuyunZhishikuDiyiBufen/__init__.py
WuyunZhishikuDiyiBufen/__main__.py
WuyunZhishikuDiyiBufen/file.epub
WuyunZhishikuDiyiBufen/index.html
WuyunZhishikuDiyiBufen/css/__init__.py
WuyunZhishikuDiyiBufen/css/annotations.css
WuyunZhishikuDiyiBufen/css/main.css
WuyunZhishikuDiyiBufen/css/normalize.css
WuyunZhishikuDiyiBufen/css/popup.css
WuyunZhishikuDiyiBufen/font/__init__.py
WuyunZhishikuDiyiBufen/font/fontello.eot
WuyunZhishikuDiyiBufen/font/fontello.svg
WuyunZhishikuDiyiBufen/font/fontello.ttf
WuyunZhishikuDiyiBufen/font/fontello.woff
WuyunZhishikuDiyiBufen/img/__init__.py
WuyunZhishikuDiyiBufen/img/annotator-glyph-sprite.png
WuyunZhishikuDiyiBufen/img/annotator-icon-sprite.png
WuyunZhishikuDiyiBufen/img/apple-touch-icon.png
WuyunZhishikuDiyiBufen/img/cancelfullscreen.png
WuyunZhishikuDiyiBufen/img/close.png
WuyunZhishikuDiyiBufen/img/fullscreen.png
WuyunZhishikuDiyiBufen/img/loader.gif
WuyunZhishikuDiyiBufen/img/menu-icon.png
WuyunZhishikuDiyiBufen/img/save.png
WuyunZhishikuDiyiBufen/img/saved.png
WuyunZhishikuDiyiBufen/img/settings-s.png
WuyunZhishikuDiyiBufen/img/settings.png
WuyunZhishikuDiyiBufen/img/star.png
WuyunZhishikuDiyiBufen/js/__init__.py
WuyunZhishikuDiyiBufen/js/epub.js
WuyunZhishikuDiyiBufen/js/epub.min.js
WuyunZhishikuDiyiBufen/js/epub.min.map
WuyunZhishikuDiyiBufen/js/hooks.min.js
WuyunZhishikuDiyiBufen/js/hooks.min.map
WuyunZhishikuDiyiBufen/js/reader.js
WuyunZhishikuDiyiBufen/js/reader.js.map
WuyunZhishikuDiyiBufen/js/reader.min.js
WuyunZhishikuDiyiBufen/js/reader.min.map
WuyunZhishikuDiyiBufen/js/hooks/__init__.py
WuyunZhishikuDiyiBufen/js/hooks/extensions/__init__.py
WuyunZhishikuDiyiBufen/js/hooks/extensions/highlight.js
WuyunZhishikuDiyiBufen/js/libs/__init__.py
WuyunZhishikuDiyiBufen/js/libs/jquery.min.js
WuyunZhishikuDiyiBufen/js/libs/localforage.min.js
WuyunZhishikuDiyiBufen/js/libs/screenfull.js
WuyunZhishikuDiyiBufen/js/libs/screenfull.min.js
WuyunZhishikuDiyiBufen/js/libs/zip.min.js
wuyun_zhishiku_diyi_bufen-2024.3.5.0.dist-info/METADATA
wuyun_zhishiku_diyi_bufen-2024.3.5.0.dist-info/WHEEL
wuyun_zhishiku_diyi_bufen-2024.3.5.0.dist-info/entry_points.txt
wuyun_zhishiku_diyi_bufen-2024.3.5.0.dist-info/top_level.txt
wuyun_zhishiku_diyi_bufen-2024.3.5.0.dist-info/RECORD
